parsetf/__init__.py
parsetf/__version__.py
parsetf/parse.so
parsetf-3.0.dist-info/LICENSE
parsetf-3.0.dist-info/METADATA
parsetf-3.0.dist-info/WHEEL
parsetf-3.0.dist-info/top_level.txt
parsetf-3.0.dist-info/RECORD
